extruct/VERSION
extruct/__init__.py
extruct/__main__.py
extruct/_extruct.py
extruct/dublincore.py
extruct/jsonld.py
extruct/microformat.py
extruct/opengraph.py
extruct/rdfa.py
extruct/tool.py
extruct/uniform.py
extruct/utils.py
extruct/w3cmicrodata.py
extruct/xmldom.py
extruct-0.15.0.dist-info/AUTHORS
extruct-0.15.0.dist-info/LICENSE
extruct-0.15.0.dist-info/METADATA
extruct-0.15.0.dist-info/WHEEL
extruct-0.15.0.dist-info/entry_points.txt
extruct-0.15.0.dist-info/top_level.txt
extruct-0.15.0.dist-info/RECORD
