Metadata-Version: 2.1
Name: extruct
Version: 0.15.0
Summary: Extract embedded metadata from HTML markup
Home-page: https://github.com/scrapinghub/extruct
Author: Scrapinghub
Author-email: info@scrapinghub.com
Maintainer: Scrapinghub
Maintainer-email: info@scrapinghub.com
Keywords: extruct
Classifier: Development Status :: 4 - Beta
Classifier: Intended Audience :: Developers
Classifier: License :: OSI Approved :: BSD License
Classifier: Natural Language :: English
Classifier: Operating System :: OS Independent
Classifier: Programming Language :: Python :: 3
Classifier: Programming Language :: Python :: 3.8
Classifier: Programming Language :: Python :: 3.9
Classifier: Programming Language :: Python :: 3.10
Classifier: Programming Language :: Python :: 3.11
License-File: LICENSE
License-File: AUTHORS
Requires-Dist: lxml
Requires-Dist: pyrdfa3
Requires-Dist: mf2py
Requires-Dist: w3lib
Requires-Dist: html-text (>=0.5.1)
Requires-Dist: six
Requires-Dist: jstyleson
Requires-Dist: rdflib (<6.0.0) ; python_version < "3.7"
Requires-Dist: rdflib-jsonld (<=0.5.0) ; python_version < "3.7"
Requires-Dist: rdflib (>=6.0.0) ; python_version >= "3.7"
Provides-Extra: cli
Requires-Dist: requests ; extra == 'cli'
